django_simple_notifications-0.1.1.dist-info/DESCRIPTION.rst
django_simple_notifications-0.1.1.dist-info/METADATA
django_simple_notifications-0.1.1.dist-info/RECORD
django_simple_notifications-0.1.1.dist-info/WHEEL
django_simple_notifications-0.1.1.dist-info/metadata.json
django_simple_notifications-0.1.1.dist-info/top_level.txt
simple_notifications/__init__.py
simple_notifications/admin.py
simple_notifications/apps.py
simple_notifications/business.py
simple_notifications/compat.py
simple_notifications/context_processors.py
simple_notifications/factories.py
simple_notifications/models.py
simple_notifications/settings.py
simple_notifications/urls.py
simple_notifications/views.py
