Metadata-Version: 2.0
Name: django-simple-notifications
Version: 0.1.1
Summary: A app package for simple notifications for django
Home-page: https://github.com/leonardoo/django-simple-notifications
Author: leonardo orozco
Author-email: you@example.com
License: MIT
Keywords: django-simple-notifications
Platform: UNKNOWN
Classifier: Development Status :: 3 - Alpha
Classifier: Framework :: Django :: 1.11
Classifier: Intended Audience :: Developers
Classifier: License :: OSI Approved :: BSD License
Classifier: Natural Language :: English
Classifier: Programming Language :: Python :: 3
Classifier: Programming Language :: Python :: 3.5
Classifier: Programming Language :: Python :: 3.6
Requires-Dist: django-model-utils (>=2.0)
